lateness/__init__.py
lateness/backends/__init__.py
lateness/backends/onnx_colbert.py
lateness/backends/torch_colbert.py
lateness/indexing/__init__.py
lateness/indexing/qdrant_indexer.py
lateness/models/__init__.py
lateness/models/model_manager.py
lateness/retrieval/__init__.py
lateness/retrieval/qdrant_retriever.py
lateness-0.1.0.dist-info/METADATA
lateness-0.1.0.dist-info/WHEEL
lateness-0.1.0.dist-info/top_level.txt
lateness-0.1.0.dist-info/RECORD
