Metadata-Version: 2.4
Name: lateness
Version: 0.1.0
Summary: Modern ColBERT for Late Interaction with native multi-vector support
Home-page: https://github.com/moderncolbert/lateness
Author: donkey stereotype
Author-email: prithivi@donkeystereotype.com
Project-URL: Bug Reports, https://github.com/moderncolbert/lateness/issues
Project-URL: Source, https://github.com/moderncolbert/lateness
Project-URL: Documentation, https://moderncolbert.github.io/lateness/
Keywords: colbert,retrieval,embeddings,information-retrieval,nlp,onnx,pytorch,qdrant
Classifier: Development Status :: 4 - Beta
Classifier: Intended Audience :: Developers
Classifier: Intended Audience :: Science/Research
Classifier: License :: OSI Approved :: Apache Software License
Classifier: Operating System :: OS Independent
Classifier: Programming Language :: Python :: 3
Classifier: Programming Language :: Python :: 3.8
Classifier: Programming Language :: Python :: 3.9
Classifier: Programming Language :: Python :: 3.10
Classifier: Programming Language :: Python :: 3.11
Classifier: Topic :: Scientific/Engineering :: Artificial Intelligence
Classifier: Topic :: Software Development :: Libraries :: Python Modules
Requires-Python: >=3.8
Requires-Dist: numpy>=1.21.0
Requires-Dist: onnxruntime>=1.15.0
Requires-Dist: tokenizers>=0.13.0
Requires-Dist: huggingface-hub>=0.16.0
Requires-Dist: tqdm>=4.64.0
Requires-Dist: qdrant-client>=1.6.0
Provides-Extra: index
Requires-Dist: torch>=1.13.0; extra == "index"
Requires-Dist: transformers>=4.21.0; extra == "index"
Requires-Dist: numpy>=1.21.0; extra == "index"
Requires-Dist: onnxruntime>=1.15.0; extra == "index"
Requires-Dist: tokenizers>=0.13.0; extra == "index"
Requires-Dist: huggingface-hub>=0.16.0; extra == "index"
Requires-Dist: tqdm>=4.64.0; extra == "index"
Requires-Dist: qdrant-client>=1.6.0; extra == "index"
Provides-Extra: all
Requires-Dist: torch>=1.13.0; extra == "all"
Requires-Dist: transformers>=4.21.0; extra == "all"
Requires-Dist: numpy>=1.21.0; extra == "all"
Requires-Dist: onnxruntime>=1.15.0; extra == "all"
Requires-Dist: tokenizers>=0.13.0; extra == "all"
Requires-Dist: huggingface-hub>=0.16.0; extra == "all"
Requires-Dist: tqdm>=4.64.0; extra == "all"
Requires-Dist: qdrant-client>=1.6.0; extra == "all"
Dynamic: author
Dynamic: author-email
Dynamic: classifier
Dynamic: description
Dynamic: description-content-type
Dynamic: home-page
Dynamic: keywords
Dynamic: project-url
Dynamic: provides-extra
Dynamic: requires-dist
Dynamic: requires-python
Dynamic: summary
